nonebot_plugin_bf1_groptools/__init__.py
nonebot_plugin_bf1_groptools-0.0.13.dist-info/METADATA
nonebot_plugin_bf1_groptools-0.0.13.dist-info/WHEEL
nonebot_plugin_bf1_groptools-0.0.13.dist-info/top_level.txt
nonebot_plugin_bf1_groptools-0.0.13.dist-info/RECORD
