Metadata-Version: 2.1
Name: nonebot-plugin-bf1-groptools
Version: 0.0.13
Summary: Nonebot plugin that verifies BF1 accounts and automatically approves group applications and changes business cards.
Author: qienoob
Author-email: 196859929@qq.com
License: apache 3.0
Requires: requests
Requires: re
Requires: nonebot2
Requires: nonebot.adapters.onebot
Requires-Dist: requests
Requires-Dist: nonebot2 (>=2.0.0-beta.1)
Requires-Dist: nonebot-adapter-onebot (<3.0.0,>=2.0.0-beta.1)
